[
  {
    "id": "flash-sale",
    "name": "Flash Sale",
    "discountType": "PERCENT",
    "discount": 50,
    "startAt": "2025-09-23T00:00:00Z",
    "endAt": "2025-09-30T23:59:59Z",
    "packages": ["package_1", "package_2", "valorant-rapid-deliver-1000"]
  },
  {
    "id": "sale-1",
    "name": "Sale 1",
    "discountType": "PERCENT",
    "discount": 10,
    "startAt": "2025-09-23T00:00:00Z",
    "endAt": "2025-10-23T23:59:59Z",
    "packages": [
      "valorant-nightfall-1000",
      "valorant-pre-order-1000",
      "lol-wildrift-1000"
    ]
  },
  {
    "id": "sale-2",
    "name": "Sale 2",
    "discountType": "FIXED",
    "discount": 10,
    "startAt": "2025-09-23T00:00:00Z",
    "endAt": "2026-09-23T23:59:59Z",
    "packages": ["lol-pc-1000", "tft-mobile-1000", "pubg-id-thai-1000"]
  }
]
